<?xml version="1.0" encoding="UTF-8" standalone="yes"?>
<w:hdr xmlns:wpc="http://schemas.microsoft.com/office/word/2010/wordprocessingCanvas" xmlns:cx="http://schemas.microsoft.com/office/drawing/2014/chartex" xmlns:cx1="http://schemas.microsoft.com/office/drawing/2015/9/8/chartex" xmlns:cx2="http://schemas.microsoft.com/office/drawing/2015/10/21/chartex" xmlns:cx3="http://schemas.microsoft.com/office/drawing/2016/5/9/chartex" xmlns:cx4="http://schemas.microsoft.com/office/drawing/2016/5/10/chartex" xmlns:cx5="http://schemas.microsoft.com/office/drawing/2016/5/11/chartex" xmlns:cx6="http://schemas.microsoft.com/office/drawing/2016/5/12/chartex" xmlns:cx7="http://schemas.microsoft.com/office/drawing/2016/5/13/chartex" xmlns:cx8="http://schemas.microsoft.com/office/drawing/2016/5/14/chartex" xmlns:mc="http://schemas.openxmlformats.org/markup-compatibility/2006" xmlns:aink="http://schemas.microsoft.com/office/drawing/2016/ink" xmlns:am3d="http://schemas.microsoft.com/office/drawing/2017/model3d" xmlns:o="urn:schemas-microsoft-com:office:office" xmlns:oel="http://schemas.microsoft.com/office/2019/extlst" xmlns:r="http://schemas.openxmlformats.org/officeDocument/2006/relationships" xmlns:m="http://schemas.openxmlformats.org/officeDocument/2006/math" xmlns:v="urn:schemas-microsoft-com:vml" xmlns:wp14="http://schemas.microsoft.com/office/word/2010/wordprocessingDrawing" xmlns:wp="http://schemas.openxmlformats.org/drawingml/2006/wordprocessingDrawing" xmlns:w10="urn:schemas-microsoft-com:office:word" xmlns:w="http://schemas.openxmlformats.org/wordprocessingml/2006/main" xmlns:w14="http://schemas.microsoft.com/office/word/2010/wordml" xmlns:w15="http://schemas.microsoft.com/office/word/2012/wordml" xmlns:w16cex="http://schemas.microsoft.com/office/word/2018/wordml/cex" xmlns:w16cid="http://schemas.microsoft.com/office/word/2016/wordml/cid" xmlns:w16="http://schemas.microsoft.com/office/word/2018/wordml" xmlns:w16sdtdh="http://schemas.microsoft.com/office/word/2020/wordml/sdtdatahash" xmlns:w16se="http://schemas.microsoft.com/office/word/2015/wordml/symex" xmlns:wpg="http://schemas.microsoft.com/office/word/2010/wordprocessingGroup" xmlns:wpi="http://schemas.microsoft.com/office/word/2010/wordprocessingInk" xmlns:wne="http://schemas.microsoft.com/office/word/2006/wordml" xmlns:wps="http://schemas.microsoft.com/office/word/2010/wordprocessingShape" mc:Ignorable="w14 w15 w16se w16cid w16 w16cex w16sdtdh wp14"><w:p w14:paraId="7819BCF4" w14:textId="1B213F53" w:rsidR="001F71C8" w:rsidRDefault="00ED670E" w:rsidP="00EF62D9"><w:pPr><w:pStyle w:val="Encabezado"/><w:tabs><w:tab w:val="clear" w:pos="4252"/><w:tab w:val="clear" w:pos="8504"/><w:tab w:val="center" w:pos="4817"/></w:tabs></w:pPr><w:r><w:rPr><w:noProof/></w:rPr><w:drawing><wp:anchor distT="0" distB="0" distL="114300" distR="114300" simplePos="0" relativeHeight="251659776" behindDoc="1" locked="0" layoutInCell="1" allowOverlap="1" wp14:anchorId="5E131FC2" wp14:editId="45063B64"><wp:simplePos x="0" y="0"/><wp:positionH relativeFrom="column"><wp:posOffset>-635</wp:posOffset></wp:positionH><wp:positionV relativeFrom="paragraph"><wp:posOffset>-1543685</wp:posOffset></wp:positionV><wp:extent cx="4662805" cy="583565"/><wp:effectExtent l="0" t="0" r="4445" b="6985"/><wp:wrapNone/><wp:docPr id="2" name="Imagen 2"/><wp:cNvGraphicFramePr><a:graphicFrameLocks xmlns:a="http://schemas.openxmlformats.org/drawingml/2006/main" noChangeAspect="1"/></wp:cNvGraphicFramePr><a:graphic xmlns:a="http://schemas.openxmlformats.org/drawingml/2006/main"><a:graphicData uri="http://schemas.openxmlformats.org/drawingml/2006/picture"><pic:pic xmlns:pic="http://schemas.openxmlformats.org/drawingml/2006/picture"><pic:nvPicPr><pic:cNvPr id="0" name="Picture 1"/><pic:cNvPicPr><a:picLocks noChangeAspect="1" noChangeArrowheads="1"/></pic:cNvPicPr></pic:nvPicPr><pic:blipFill><a:blip r:embed="rId1"><a:extLst><a:ext uri="{28A0092B-C50C-407E-A947-70E740481C1C}"><a14:useLocalDpi xmlns:a14="http://schemas.microsoft.com/office/drawing/2010/main" val="0"/></a:ext></a:extLst></a:blip><a:srcRect/><a:stretch><a:fillRect/></a:stretch></pic:blipFill><pic:spPr bwMode="auto"><a:xfrm><a:off x="0" y="0"/><a:ext cx="4662805" cy="583565"/></a:xfrm><a:prstGeom prst="rect"><a:avLst/></a:prstGeom><a:noFill/></pic:spPr></pic:pic></a:graphicData></a:graphic><wp14:sizeRelH relativeFrom="page"><wp14:pctWidth>0</wp14:pctWidth></wp14:sizeRelH><wp14:sizeRelV relativeFrom="page"><wp14:pctHeight>0</wp14:pctHeight></wp14:sizeRelV></wp:anchor></w:drawing></w:r><w:r w:rsidR="00B55607"><w:rPr><w:noProof/><w:lang w:eastAsia="es-MX"/></w:rPr><mc:AlternateContent><mc:Choice Requires="wps"><w:drawing><wp:anchor distT="0" distB="0" distL="114300" distR="114300" simplePos="0" relativeHeight="251657728" behindDoc="0" locked="0" layoutInCell="1" allowOverlap="1" wp14:anchorId="1EB6341D" wp14:editId="4EF9FFD2"><wp:simplePos x="0" y="0"/><wp:positionH relativeFrom="column"><wp:posOffset>2019300</wp:posOffset></wp:positionH><wp:positionV relativeFrom="paragraph"><wp:posOffset>-546100</wp:posOffset></wp:positionV><wp:extent cx="4257675" cy="497840"/><wp:effectExtent l="0" t="0" r="0" b="0"/><wp:wrapNone/><wp:docPr id="1" name="Text Box 5"/><wp:cNvGraphicFramePr><a:graphicFrameLocks xmlns:a="http://schemas.openxmlformats.org/drawingml/2006/main"/></wp:cNvGraphicFramePr><a:graphic xmlns:a="http://schemas.openxmlformats.org/drawingml/2006/main"><a:graphicData uri="http://schemas.microsoft.com/office/word/2010/wordprocessingShape"><wps:wsp><wps:cNvSpPr txBox="1"><a:spLocks noChangeArrowheads="1"/></wps:cNvSpPr><wps:spPr bwMode="auto"><a:xfrm><a:off x="0" y="0"/><a:ext cx="4257675" cy="497840"/></a:xfrm><a:prstGeom prst="rect"><a:avLst/></a:prstGeom><a:noFill/><a:ln><a:noFill/></a:ln><a:extLst><a:ext uri="{909E8E84-426E-40DD-AFC4-6F175D3DCCD1}"><a14:hiddenFill xmlns:a14="http://schemas.microsoft.com/office/drawing/2010/main"><a:solidFill><a:srgbClr val="FFFFFF"/></a:solidFill></a14:hiddenFill></a:ext><a:ext uri="{91240B29-F687-4F45-9708-019B960494DF}"><a14:hiddenLine xmlns:a14="http://schemas.microsoft.com/office/drawing/2010/main" w="9525"><a:solidFill><a:srgbClr val="000000"/></a:solidFill><a:miter lim="800000"/><a:headEnd/><a:tailEnd/></a14:hiddenLine></a:ext></a:extLst></wps:spPr><wps:txbx><w:txbxContent><w:p w14:paraId="4FED516D" w14:textId="77777777" w:rsidR="001F71C8" w:rsidRPr="002C3C51" w:rsidRDefault="001F71C8" w:rsidP="007379F8"><w:pPr><w:ind w:right="75"/><w:jc w:val="right"/><w:rPr><w:rFonts w:ascii="Montserrat Medium" w:hAnsi="Montserrat Medium" w:cs="Arial"/><w:b/><w:color w:val="595959" w:themeColor="text1" w:themeTint="A6"/><w:sz w:val="16"/><w:szCs w:val="16"/></w:rPr></w:pPr><w:r w:rsidRPr="00B55607"><w:rPr><w:rFonts w:ascii="Montserrat Medium" w:hAnsi="Montserrat Medium" w:cs="Arial"/><w:b/><w:color w:val="595959" w:themeColor="text1" w:themeTint="A6"/><w:sz w:val="18"/><w:szCs w:val="16"/></w:rPr><w:t xml:space="preserve">Instituto Tecnol贸gico de </w:t></w:r><w:r w:rsidR="0050206A" w:rsidRPr="00B55607"><w:rPr><w:rFonts w:ascii="Montserrat Medium" w:hAnsi="Montserrat Medium" w:cs="Arial"/><w:b/><w:color w:val="595959" w:themeColor="text1" w:themeTint="A6"/><w:sz w:val="18"/><w:szCs w:val="16"/></w:rPr><w:t>Pabell贸n de Arteaga</w:t></w:r></w:p><w:p w14:paraId="5E59A5BA" w14:textId="77777777" w:rsidR="001F71C8" w:rsidRPr="00A44E22" w:rsidRDefault="001F71C8" w:rsidP="007379F8"><w:pPr><w:ind w:right="75"/><w:contextualSpacing/><w:jc w:val="right"/><w:rPr><w:rFonts w:ascii="Adobe Caslon Pro" w:hAnsi="Adobe Caslon Pro" w:cs="Arial"/><w:color w:val="808080"/><w:sz w:val="14"/><w:szCs w:val="14"/></w:rPr></w:pPr></w:p><w:p w14:paraId="3037B653" w14:textId="77777777" w:rsidR="001F71C8" w:rsidRPr="00820EA8" w:rsidRDefault="001F71C8" w:rsidP="007379F8"><w:pPr><w:jc w:val="right"/><w:rPr><w:rFonts w:ascii="EurekaSans-Light" w:hAnsi="EurekaSans-Light" w:cs="Arial"/><w:sz w:val="20"/><w:szCs w:val="20"/></w:rPr></w:pPr></w:p><w:p w14:paraId="645A5B40" w14:textId="77777777" w:rsidR="001F71C8" w:rsidRDefault="001F71C8" w:rsidP="007379F8"><w:pPr><w:jc w:val="right"/></w:pPr></w:p></w:txbxContent></wps:txbx><wps:bodyPr rot="0" vert="horz" wrap="square" lIns="91440" tIns="45720" rIns="91440" bIns="45720" anchor="t" anchorCtr="0" upright="1"><a:noAutofit/></wps:bodyPr></wps:wsp></a:graphicData></a:graphic><wp14:sizeRelH relativeFrom="page"><wp14:pctWidth>0</wp14:pctWidth></wp14:sizeRelH><wp14:sizeRelV relativeFrom="page"><wp14:pctHeight>0</wp14:pctHeight></wp14:sizeRelV></wp:anchor></w:drawing></mc:Choice><mc:Fallback><w:pict><v:shapetype w14:anchorId="1EB6341D" id="_x0000_t202" coordsize="21600,21600" o:spt="202" path="m,l,21600r21600,l21600,xe"><v:stroke joinstyle="miter"/><v:path gradientshapeok="t" o:connecttype="rect"/></v:shapetype><v:shape id="Text Box 5" o:spid="_x0000_s1026" type="#_x0000_t202" style="position:absolute;margin-left:159pt;margin-top:-43pt;width:335.25pt;height:39.2pt;z-index:251657728;visibility:visible;mso-wrap-style:square;mso-width-percent:0;mso-height-percent:0;mso-wrap-distance-left:9pt;mso-wrap-distance-top:0;mso-wrap-distance-right:9pt;mso-wrap-distance-bottom:0;mso-position-horizontal:absolute;mso-position-horizontal-relative:text;mso-position-vertical:absolute;mso-position-vertical-relative:text;mso-width-percent:0;mso-height-percent:0;mso-width-relative:page;mso-height-relative:page;v-text-anchor:top" o:gfxdata="UEsDBBQABgAIAAAAIQC2gziS/gAAAOEBAAATAAAAW0NvbnRlbnRfVHlwZXNdLnhtbJSRQU7DMBBF&#xA;90jcwfIWJU67QAgl6YK0S0CoHGBkTxKLZGx5TGhvj5O2G0SRWNoz/78nu9wcxkFMGNg6quQqL6RA&#xA;0s5Y6ir5vt9lD1JwBDIwOMJKHpHlpr69KfdHjyxSmriSfYz+USnWPY7AufNIadK6MEJMx9ApD/oD&#xA;OlTrorhX2lFEilmcO2RdNtjC5xDF9pCuTyYBB5bi6bQ4syoJ3g9WQ0ymaiLzg5KdCXlKLjvcW893&#xA;SUOqXwnz5DrgnHtJTxOsQfEKIT7DmDSUCaxw7Rqn8787ZsmRM9e2VmPeBN4uqYvTtW7jvijg9N/y&#xA;JsXecLq0q+WD6m8AAAD//wMAUEsDBBQABgAIAAAAIQA4/SH/1gAAAJQBAAALAAAAX3JlbHMvLnJl&#xA;bHOkkMFqwzAMhu+DvYPRfXGawxijTi+j0GvpHsDYimMaW0Yy2fr2M4PBMnrbUb/Q94l/f/hMi1qR&#xA;JVI2sOt6UJgd+ZiDgffL8ekFlFSbvV0oo4EbChzGx4f9GRdb25HMsYhqlCwG5lrLq9biZkxWOiqY&#xA;22YiTra2kYMu1l1tQD30/bPm3wwYN0x18gb45AdQl1tp5j/sFB2T0FQ7R0nTNEV3j6o9feQzro1i&#xA;OWA14Fm+Q8a1a8+Bvu/d/dMb2JY5uiPbhG/ktn4cqGU/er3pcvwCAAD//wMAUEsDBBQABgAIAAAA&#xA;IQCzQsPn4QEAAKEDAAAOAAAAZHJzL2Uyb0RvYy54bWysU8Fu2zAMvQ/YPwi6L04Cp2mNOEXXosOA&#xA;bh3Q7QNkWbKF2aJGKbGzrx8lp2m23YpeBImkH997pDfXY9+xvUJvwJZ8MZtzpqyE2tim5D++33+4&#xA;5MwHYWvRgVUlPyjPr7fv320GV6gltNDVChmBWF8MruRtCK7IMi9b1Qs/A6csJTVgLwI9sclqFAOh&#xA;9122nM8vsgGwdghSeU/RuynJtwlfayXDo9ZeBdaVnLiFdGI6q3hm240oGhSuNfJIQ7yCRS+MpaYn&#xA;qDsRBNuh+Q+qNxLBgw4zCX0GWhupkgZSs5j/o+apFU4lLWSOdyeb/NvByq/7J/cNWRg/wkgDTCK8&#xA;ewD50zMLt62wjbpBhKFVoqbGi2hZNjhfHD+NVvvCR5Bq+AI1DVnsAiSgUWMfXSGdjNBpAIeT6WoM&#xA;TFIwX67WF+sVZ5Jy+dX6Mk9TyUTx/LVDHz4p6Fm8lBxpqAld7B98iGxE8VwSm1m4N12XBtvZvwJU&#xA;GCOJfSQ8UQ9jNVJ1VFFBfSAdCNOe0F7TpQX8zdlAO1Jy/2snUHHWfbbkxdUiJ7IspEe+Wi/pgeeZ&#xA;6jwjrCSokgfOputtmBZx59A0LXWa3LdwQ/5pk6S9sDrypj1Iio87Gxft/J2qXv6s7R8AAAD//wMA&#xA;UEsDBBQABgAIAAAAIQAp7UEN3gAAAAoBAAAPAAAAZHJzL2Rvd25yZXYueG1sTI9BT8MwDIXvSPyH&#xA;yEjctmTASlaaTgjEFbTBJnHLGq+taJyqydby7zEnuNl+T8/fK9aT78QZh9gGMrCYKxBIVXAt1QY+&#xA;3l9mGkRMlpztAqGBb4ywLi8vCpu7MNIGz9tUCw6hmFsDTUp9LmWsGvQ2zkOPxNoxDN4mXodausGO&#xA;HO47eaNUJr1tiT80tsenBquv7ckb2L0eP/d36q1+9st+DJOS5FfSmOur6fEBRMIp/ZnhF5/RoWSm&#xA;QziRi6IzcLvQ3CUZmOmMB3astF6COPDlPgNZFvJ/hfIHAAD//wMAUEsBAi0AFAAGAAgAAAAhALaD&#xA;OJL+AAAA4QEAABMAAAAAAAAAAAAAAAAAAAAAAFtDb250ZW50X1R5cGVzXS54bWxQSwECLQAUAAYA&#xA;CAAAACEAOP0h/9YAAACUAQAACwAAAAAAAAAAAAAAAAAvAQAAX3JlbHMvLnJlbHNQSwECLQAUAAYA&#xA;CAAAACEAs0LD5+EBAAChAwAADgAAAAAAAAAAAAAAAAAuAgAAZHJzL2Uyb0RvYy54bWxQSwECLQAU&#xA;AAYACAAAACEAKe1BDd4AAAAKAQAADwAAAAAAAAAAAAAAAAA7BAAAZHJzL2Rvd25yZXYueG1sUEsF&#xA;BgAAAAAEAAQA8wAAAEYFAAAAAA==&#xA;" filled="f" stroked="f"><v:textbox><w:txbxContent><w:p w14:paraId="4FED516D" w14:textId="77777777" w:rsidR="001F71C8" w:rsidRPr="002C3C51" w:rsidRDefault="001F71C8" w:rsidP="007379F8"><w:pPr><w:ind w:right="75"/><w:jc w:val="right"/><w:rPr><w:rFonts w:ascii="Montserrat Medium" w:hAnsi="Montserrat Medium" w:cs="Arial"/><w:b/><w:color w:val="595959" w:themeColor="text1" w:themeTint="A6"/><w:sz w:val="16"/><w:szCs w:val="16"/></w:rPr></w:pPr><w:r w:rsidRPr="00B55607"><w:rPr><w:rFonts w:ascii="Montserrat Medium" w:hAnsi="Montserrat Medium" w:cs="Arial"/><w:b/><w:color w:val="595959" w:themeColor="text1" w:themeTint="A6"/><w:sz w:val="18"/><w:szCs w:val="16"/></w:rPr><w:t xml:space="preserve">Instituto Tecnol贸gico de </w:t></w:r><w:r w:rsidR="0050206A" w:rsidRPr="00B55607"><w:rPr><w:rFonts w:ascii="Montserrat Medium" w:hAnsi="Montserrat Medium" w:cs="Arial"/><w:b/><w:color w:val="595959" w:themeColor="text1" w:themeTint="A6"/><w:sz w:val="18"/><w:szCs w:val="16"/></w:rPr><w:t>Pabell贸n de Arteaga</w:t></w:r></w:p><w:p w14:paraId="5E59A5BA" w14:textId="77777777" w:rsidR="001F71C8" w:rsidRPr="00A44E22" w:rsidRDefault="001F71C8" w:rsidP="007379F8"><w:pPr><w:ind w:right="75"/><w:contextualSpacing/><w:jc w:val="right"/><w:rPr><w:rFonts w:ascii="Adobe Caslon Pro" w:hAnsi="Adobe Caslon Pro" w:cs="Arial"/><w:color w:val="808080"/><w:sz w:val="14"/><w:szCs w:val="14"/></w:rPr></w:pPr></w:p><w:p w14:paraId="3037B653" w14:textId="77777777" w:rsidR="001F71C8" w:rsidRPr="00820EA8" w:rsidRDefault="001F71C8" w:rsidP="007379F8"><w:pPr><w:jc w:val="right"/><w:rPr><w:rFonts w:ascii="EurekaSans-Light" w:hAnsi="EurekaSans-Light" w:cs="Arial"/><w:sz w:val="20"/><w:szCs w:val="20"/></w:rPr></w:pPr></w:p><w:p w14:paraId="645A5B40" w14:textId="77777777" w:rsidR="001F71C8" w:rsidRDefault="001F71C8" w:rsidP="007379F8"><w:pPr><w:jc w:val="right"/></w:pPr></w:p></w:txbxContent></v:textbox></v:shape></w:pict></mc:Fallback></mc:AlternateContent></w:r></w:p></w:hdr>